kdocpyxl/__init__.py
kdocpyxl/read_data.py
kdocpyxl/wps_cloud_excel.py
kdocpyxl/write_data.py
kdocpyxl/wrtie_data.py
kdocpyxl-0.0.2.dist-info/LICENSE
kdocpyxl-0.0.2.dist-info/METADATA
kdocpyxl-0.0.2.dist-info/WHEEL
kdocpyxl-0.0.2.dist-info/top_level.txt
kdocpyxl-0.0.2.dist-info/RECORD
