Metadata-Version: 2.1
Name: kdocpyxl
Version: 0.0.2
Summary: Kingsoft cloud document excel Python read and write library
Home-page: https://github.com/silverze/kdocpyxl
Author: silverze
Author-email: silverze@foxmail.com
Classifier: Programming Language :: Python :: 3
Classifier: License :: OSI Approved :: MIT License
Classifier: Operating System :: OS Independent
Requires-Python: >=3.6
License-File: LICENSE
